tts_stt_tools/__init__.py
tts_stt_tools/modelhelper.py
tts_stt_tools/stt.py
tts_stt_tools/tts.py
tts_stt_tools/voicemodelcopier.py
tts_stt_tools-1.0.7.dist-info/METADATA
tts_stt_tools-1.0.7.dist-info/WHEEL
tts_stt_tools-1.0.7.dist-info/entry_points.txt
tts_stt_tools-1.0.7.dist-info/top_level.txt
tts_stt_tools-1.0.7.dist-info/RECORD
