Metadata-Version: 2.1
Name: tts-stt-tools
Version: 1.0.7
Summary: A package for text-to-speech and speech-to-text tools
Home-page: https://github.com/Sainag2473/tts-stt-tools
Author: Sainag
Author-email: sainag268@gmail.com
License: UNKNOWN
Platform: UNKNOWN
Classifier: Programming Language :: Python :: 3
Classifier: Programming Language :: Python :: 3.9
Classifier: Operating System :: OS Independent
Classifier: Development Status :: 3 - Alpha
Requires-Python: >=3.9
Requires-Dist: pip>=24.2
Requires-Dist: tts-stt-tools>=0.1.6
Requires-Dist: mycroft-mimic3-tts
Requires-Dist: ipykernel
Requires-Dist: jupyterlab
Requires-Dist: pydub
Requires-Dist: vosk
Requires-Dist: pytest
